cimrdfpy/__init__.py
cimrdfpy/generator.py
cimrdf.py-2.1.dist-info/LICENSE
cimrdf.py-2.1.dist-info/METADATA
cimrdf.py-2.1.dist-info/WHEEL
cimrdf.py-2.1.dist-info/entry_points.txt
cimrdf.py-2.1.dist-info/top_level.txt
cimrdf.py-2.1.dist-info/zip-safe
cimrdf.py-2.1.dist-info/RECORD
