Metadata-Version: 2.1
Name: cimrdf.py
Version: 2.1
Summary: Generate Python data structures from CIM RDF profiles, parse and serialize CIM-compliant information objects, according to IEC 61970-501 standard
Home-page: https://github.com/bressanmarcos/cimrdf.py
Author: Marcos Bressan
Author-email: bressanmarcos@alu.ufc.br
License: UNKNOWN
Platform: UNKNOWN
Classifier: Programming Language :: Python :: 3
Classifier: License :: OSI Approved :: MIT License
Classifier: Operating System :: OS Independent
Requires-Python: >=3.6
